odoo8_addon_hr_employee_data_from_work_address-8.0.1.0.0.99.dev18-nspkg.pth
odoo_addons/hr_employee_data_from_work_address/README.rst
odoo_addons/hr_employee_data_from_work_address/__init__.py
odoo_addons/hr_employee_data_from_work_address/__openerp__.py
odoo_addons/hr_employee_data_from_work_address/init_hook.py
odoo_addons/hr_employee_data_from_work_address/data/res_partner_category.xml
odoo_addons/hr_employee_data_from_work_address/i18n/ar.po
odoo_addons/hr_employee_data_from_work_address/i18n/de.po
odoo_addons/hr_employee_data_from_work_address/i18n/es.po
odoo_addons/hr_employee_data_from_work_address/i18n/fi.po
odoo_addons/hr_employee_data_from_work_address/i18n/fr.po
odoo_addons/hr_employee_data_from_work_address/i18n/hr_employee_data_from_work_address.pot
odoo_addons/hr_employee_data_from_work_address/i18n/it.po
odoo_addons/hr_employee_data_from_work_address/i18n/nl.po
odoo_addons/hr_employee_data_from_work_address/i18n/nl_NL.po
odoo_addons/hr_employee_data_from_work_address/i18n/pt_BR.po
odoo_addons/hr_employee_data_from_work_address/i18n/ro.po
odoo_addons/hr_employee_data_from_work_address/i18n/sl.po
odoo_addons/hr_employee_data_from_work_address/i18n/tr_TR.po
odoo_addons/hr_employee_data_from_work_address/models/__init__.py
odoo_addons/hr_employee_data_from_work_address/models/hr_employee.py
odoo_addons/hr_employee_data_from_work_address/static/description/icon.png
odoo_addons/hr_employee_data_from_work_address/tests/__init__.py
odoo_addons/hr_employee_data_from_work_address/tests/test_hr_employee_data_from_work_address.py
odoo_addons/hr_employee_data_from_work_address/views/hr_employee.xml
odoo_addons/hr_employee_data_from_work_address/views/res_users.xml
odoo8_addon_hr_employee_data_from_work_address-8.0.1.0.0.99.dev18.dist-info/METADATA
odoo8_addon_hr_employee_data_from_work_address-8.0.1.0.0.99.dev18.dist-info/WHEEL
odoo8_addon_hr_employee_data_from_work_address-8.0.1.0.0.99.dev18.dist-info/namespace_packages.txt
odoo8_addon_hr_employee_data_from_work_address-8.0.1.0.0.99.dev18.dist-info/top_level.txt
odoo8_addon_hr_employee_data_from_work_address-8.0.1.0.0.99.dev18.dist-info/RECORD
